opentelemetry/instrumentation/bedrock/__init__.py
opentelemetry/instrumentation/bedrock/config.py
opentelemetry/instrumentation/bedrock/event_emitter.py
opentelemetry/instrumentation/bedrock/event_models.py
opentelemetry/instrumentation/bedrock/guardrail.py
opentelemetry/instrumentation/bedrock/prompt_caching.py
opentelemetry/instrumentation/bedrock/reusable_streaming_body.py
opentelemetry/instrumentation/bedrock/span_utils.py
opentelemetry/instrumentation/bedrock/streaming_wrapper.py
opentelemetry/instrumentation/bedrock/utils.py
opentelemetry/instrumentation/bedrock/version.py
opentelemetry_instrumentation_bedrock-0.51.1.dist-info/METADATA
opentelemetry_instrumentation_bedrock-0.51.1.dist-info/WHEEL
opentelemetry_instrumentation_bedrock-0.51.1.dist-info/entry_points.txt
opentelemetry_instrumentation_bedrock-0.51.1.dist-info/RECORD
